CONTRIBUTORS.txt
MANIFEST.in
README.txt
setup.cfg
setup.py
zettwerk.clickmap-configure.zcml
docs/HISTORY.txt
docs/INSTALL.txt
docs/LICENSE.GPL
docs/LICENSE.txt
zettwerk/__init__.py
zettwerk.clickmap.egg-info/PKG-INFO
zettwerk.clickmap.egg-info/SOURCES.txt
zettwerk.clickmap.egg-info/dependency_links.txt
zettwerk.clickmap.egg-info/entry_points.txt
zettwerk.clickmap.egg-info/namespace_packages.txt
zettwerk.clickmap.egg-info/not-zip-safe
zettwerk.clickmap.egg-info/paster_plugins.txt
zettwerk.clickmap.egg-info/requires.txt
zettwerk.clickmap.egg-info/top_level.txt
zettwerk/clickmap/ClickmapTool.py
zettwerk/clickmap/__init__.py
zettwerk/clickmap/configure.zcml
zettwerk/clickmap/drawer.py
zettwerk/clickmap/interfaces.py
zettwerk/clickmap/tests.py
zettwerk/clickmap/tool.gif
zettwerk/clickmap/vocabularies.py
zettwerk/clickmap/z.png
zettwerk/clickmap/browser/__init__.py
zettwerk/clickmap/browser/clickmap.py
zettwerk/clickmap/browser/clickmap_anonymview.py
zettwerk/clickmap/browser/clickmap_js_defines.pt
zettwerk/clickmap/browser/configure.zcml
zettwerk/clickmap/browser/javascripts/clickmap.js
zettwerk/clickmap/browser/stylesheets/clickmap_testing.css
zettwerk/clickmap/profiles/default/controlpanel.xml
zettwerk/clickmap/profiles/default/cssregistry.xml
zettwerk/clickmap/profiles/default/jsregistry.xml
zettwerk/clickmap/profiles/default/metadata.xml
zettwerk/clickmap/profiles/default/toolset.xml
zettwerk/clickmap/tests/__init__.py
zettwerk/clickmap/tests/base.py
zettwerk/clickmap/tests/test_doctest.py