Metadata-Version: 1.0
Name: zettwerk.clickmap
Version: 0.13
Summary: Adding a simple clickmap/heatmap to plone 4
Home-page: http://svn.plone.org/svn/collective/zettwerk.ui
Author: zettwerk GmbH
Author-email: jk@zettwerk.com
License: GPL
Keywords: plone
Platform: UNKNOWN
Classifier: Framework :: Plone
Classifier: Programming Language :: Python
